artella/__init__.py
artella/plugins/__init__.py
artella/plugins/about/__init__.py
artella/plugins/about/__version__.py
artella/plugins/about/_version.py
artella/plugins/about/about.py
artella/plugins/about/artella-plugin.json
artella/plugins/about/resources/about.png
tests/__init__.py
tests/test_plugin.py
artella_plugins_about-1.0.3.dist-info/METADATA
artella_plugins_about-1.0.3.dist-info/WHEEL
artella_plugins_about-1.0.3.dist-info/top_level.txt
artella_plugins_about-1.0.3.dist-info/RECORD
