Metadata-Version: 2.1
Name: artella-plugins-about
Version: 1.0.3
Summary: Artella Plugin that allows to show information about the current installed Artella.
Home-page: https://github.com/artella/artella-plugins-about
Author: Artella, Inc
Author-email: support@artella.com
License: UNKNOWN
Platform: UNKNOWN
Requires-Dist: artella-plugins-core
Provides-Extra: dev
Requires-Dist: wheel ; extra == 'dev'
Provides-Extra: test
Requires-Dist: pytest ; extra == 'test'
